amivcrm/__init__.py
amivcrm-0.2.0.dist-info/METADATA
amivcrm-0.2.0.dist-info/RECORD
amivcrm-0.2.0.dist-info/WHEEL
amivcrm-0.2.0.dist-info/top_level.txt
