Metadata-Version: 2.1
Name: amivcrm
Version: 0.2.0
Summary: A simple connector to the AMIV SugarCRM
Home-page: https://gitlab.ethz.ch/amiv/kontakt/amiv-crm-connector
Author: Alexander Dietmüller
License: UNKNOWN
Platform: UNKNOWN
Requires-Dist: suds-jurko (>=0.6)
